flask_umami/__init__.py
flask_umami-0.1.4.dist-info/licenses/LICENSE
flask_umami-0.1.4.dist-info/METADATA
flask_umami-0.1.4.dist-info/WHEEL
flask_umami-0.1.4.dist-info/top_level.txt
flask_umami-0.1.4.dist-info/RECORD
