Metadata-Version: 2.4
Name: Flask-Umami
Version: 0.1.4
Summary: An easy to use Flask extension for Umami analytics
Author: ShyMike
License: AGPL-3.0
Project-URL: Source, https://github.com/ImShyMike/Flask-Umami
Classifier: Framework :: Flask
Classifier: Operating System :: OS Independent
Classifier: Programming Language :: Python :: 3
Requires-Python: >=3.10
License-File: LICENSE
Requires-Dist: bs4
Requires-Dist: flask
Dynamic: license-file
